versapy/__init__.py
versapy/main.py
versapy/src/config.py
versapy/src/api/event.py
versapy/src/api/server.py
versapy/src/api/shared_value.py
versapy/src/services/storage.py
versapy-1.0.0.dist-info/METADATA
versapy-1.0.0.dist-info/WHEEL
versapy-1.0.0.dist-info/top_level.txt
versapy-1.0.0.dist-info/RECORD
