Metadata-Version: 2.4
Name: versapy
Version: 1.0.0
Summary: Lightweight framework for desktop apps with web UI.
Author-email: lso <lso.contact@proton.me>
License-Expression: MIT
Requires-Python: >=3.9
Requires-Dist: python-socketio
Requires-Dist: pywebview
Requires-Dist: pyinstaller
Requires-Dist: uvicorn
Requires-Dist: fastapi
